mvsdk/__init__.py
mvsdk/api/__init__.py
mvsdk/rest/__init__.py
mvsdk/rest/asset/__init__.py
mvsdk/rest/attribute/__init__.py
mvsdk/rest/bulk/__init__.py
mvsdk/rest/category/__init__.py
mvsdk/rest/connect/__init__.py
mvsdk/rest/direct_link/__init__.py
mvsdk/rest/keyword/__init__.py
mvsdk/rest/keyword_group/__init__.py
mvsdk/rest/org_unit/__init__.py
mvsdk/rest/user/__init__.py
mvsdk/rest/user_group/__init__.py
mvsdk-0.0.9.dist-info/METADATA
mvsdk-0.0.9.dist-info/WHEEL
mvsdk-0.0.9.dist-info/top_level.txt
mvsdk-0.0.9.dist-info/RECORD
